pyzoom/__init__.py
pyzoom/_base.py
pyzoom/_client.py
pyzoom/err.py
pyzoom/oauth.py
pyzoom/schemas.py
pyzoom-1.0.8.dist-info/METADATA
pyzoom-1.0.8.dist-info/WHEEL
pyzoom-1.0.8.dist-info/RECORD
