Metadata-Version: 2.1
Name: pyzoom
Version: 1.0.8
Summary: Python wrapper for Zoom Video API
Home-page: https://github.com/licht1stein/pyzoom
License: MIT
Author: MB
Author-email: mb@blaster.ai
Requires-Python: >=3.7,<4.0
Classifier: License :: OSI Approved :: MIT License
Classifier: Programming Language :: Python :: 3
Classifier: Programming Language :: Python :: 3.7
Classifier: Programming Language :: Python :: 3.8
Classifier: Programming Language :: Python :: 3.9
Classifier: Programming Language :: Python :: 3.10
Classifier: Programming Language :: Python :: 3.11
Requires-Dist: attrs
Requires-Dist: cachetools (>=4.1,<6.0)
Requires-Dist: pydantic (>=2.4.2,<3.0.0)
Requires-Dist: requests (>=2.31.0,<3.0.0)
Requires-Dist: shortuuid (>=1.0.1,<2.0.0)
Requires-Dist: typing-extensions (>=3.7.4,<5.0.0)
